loggable/__init__.py
loggable/__version__.py
loggable_jdv-0.1.7.dist-info/WHEEL
loggable_jdv-0.1.7.dist-info/METADATA
loggable_jdv-0.1.7.dist-info/RECORD
